libsvm_official-3.37.0.dist-info/RECORD
libsvm_official-3.37.0.dist-info/WHEEL
libsvm_official-3.37.0.dist-info/top_level.txt
libsvm_official-3.37.0.dist-info/METADATA
libsvm_official-3.37.0.dist-info/licenses/LICENSE
libsvm/commonutil.py
libsvm/__init__.py
libsvm/svmutil.py
libsvm/clib.cpython-311-darwin.so
libsvm/svm.py
libsvm/.dylibs/libgomp.1.dylib
