Metadata-Version: 2.1
Name: libsvm-official
Version: 3.37.0
Summary: Python binding of LIBSVM
Home-page: https://www.csie.ntu.edu.tw/~cjlin/libsvm
Author: ML group @ National Taiwan University
Author-email: cjlin@csie.ntu.edu.tw
License: BSD-3-Clause
License-File: LICENSE
Requires-Dist: scipy
